smaz.cpython-310-x86_64-linux-gnu.so
smaz_py3-1.1.3.dist-info/RECORD
smaz_py3-1.1.3.dist-info/top_level.txt
smaz_py3-1.1.3.dist-info/WHEEL
smaz_py3-1.1.3.dist-info/LICENSE.md
smaz_py3-1.1.3.dist-info/METADATA
