Metadata-Version: 2.1
Name: smaz-py3
Version: 1.1.3
Summary: Small string compression using smaz, supports Python 3.
Home-page: https://github.com/originell/smaz-py3
Download-URL: https://github.com/originell/smaz-py3/tarball/1.1.3
Author: Luis Nell
Author-email: luis@originell.org
License: BSD
Keywords: smaz string compression
Classifier: Development Status :: 5 - Production/Stable
Classifier: Intended Audience :: Developers
Classifier: Programming Language :: Python :: 3
Classifier: License :: OSI Approved :: BSD License
Classifier: License :: OSI Approved :: MIT License
Requires-Python: >=3.7
License-File: LICENSE.md
